<annotation>
	<folder>Argyreus hyperbius-1300张</folder>
	<filename>Argyreus hyperbius (364).jpg</filename>
	<path>C:\machine\蝴蝶\Argyreus hyperbius-1300张\Argyreus hyperbius (364).jpg</path>
	<source>
		<database>Unknown</database>
	</source>
	<size>
		<width>611</width>
		<height>449</height>
		<depth>3</depth>
	</size>
	<segmented>0</segmented>
	<object>
		<name>Argyreus hyperbius</name>
		<pose>Unspecified</pose>
		<truncated>0</truncated>
		<difficult>0</difficult>
		<bndbox>
			<xmin>194</xmin>
			<ymin>133</ymin>
			<xmax>378</xmax>
			<ymax>265</ymax>
		</bndbox>
	</object>
	<object>
		<name>butterfly</name>
		<pose>Unspecified</pose>
		<truncated>0</truncated>
		<difficult>0</difficult>
		<bndbox>
			<xmin>192</xmin>
			<ymin>131</ymin>
			<xmax>376</xmax>
			<ymax>263</ymax>
		</bndbox>
	</object>
</annotation>
